libcurl/__about__.py
libcurl/__config__.py
libcurl/__init__.py
libcurl/_config.py
libcurl/_ct.py
libcurl/_curl.py
libcurl/_curlver.py
libcurl/_dll.py
libcurl/_easy.py
libcurl/_header.py
libcurl/_mprintf.py
libcurl/_multi.py
libcurl/_options.py
libcurl/_system.py
libcurl/_typecheck.py
libcurl/_urlapi.py
libcurl/_websockets.py
libcurl/libcurl.cfg
libcurl/_platform/__init__.py
libcurl/_platform/_limits.py
libcurl/_platform/_platform.py
libcurl/_platform/curl-ca-bundle.crt
libcurl/_platform/_linux/__init__.py
libcurl/_platform/_linux/x64/libcurl.so.4
libcurl/_platform/_linux/x64/libnghttp2.so.14
libcurl/_platform/_linux/x64/libpsl.so.5
libcurl/_platform/_linux/x64/librtmp.so.1
libcurl/_platform/_linux/x86/libcurl.so.4
libcurl/_platform/_linux/x86/libnghttp2.so.14
libcurl/_platform/_linux/x86/libpsl.so.5
libcurl/_platform/_linux/x86/librtmp.so.1
libcurl/_platform/_macos/__init__.py
libcurl/_platform/_macos/x64/10.9/.keep
libcurl/_platform/_macos/x86/10.9/.keep
libcurl/_platform/_windows/__init__.py
libcurl/_platform/_windows/_win32.py
libcurl/_platform/_windows/x64/libcurl-x64.def
libcurl/_platform/_windows/x64/libcurl-x64.dll
libcurl/_platform/_windows/x86/libcurl.def
libcurl/_platform/_windows/x86/libcurl.dll
libcurl_ct-8.12.1.4b1.dist-info/licenses/COPYING
libcurl_ct-8.12.1.4b1.dist-info/licenses/LICENSE
libcurl_ct-8.12.1.4b1.dist-info/METADATA
libcurl_ct-8.12.1.4b1.dist-info/WHEEL
libcurl_ct-8.12.1.4b1.dist-info/top_level.txt
libcurl_ct-8.12.1.4b1.dist-info/RECORD
