Metadata-Version: 2.4
Name: libcurl-ct
Version: 8.12.1.4b1
Summary: Python binding for the libcurl C library.
Author: Adam Karpierz
Author-email: adam@karpierz.net
Maintainer: Adam Karpierz
Maintainer-email: adam@karpierz.net
License: MIT License ; https://opensource.org/license/mit
Project-URL: Homepage, https://pypi.org/project/libcurl-ct/
Project-URL: Documentation, https://libcurl.readthedocs.io/
Project-URL: Download, https://pypi.org/project/libcurl-ct/
Project-URL: Source, https://github.com/karpierz/libcurl
Project-URL: Issues, https://github.com/karpierz/libcurl/issues
Keywords: curl,libcurl
Platform: any
Classifier: Development Status :: 4 - Beta
Classifier: Intended Audience :: Developers
Classifier: License :: OSI Approved :: MIT License
Classifier: Operating System :: OS Independent
Classifier: Natural Language :: Polish
Classifier: Programming Language :: Python
Classifier: Programming Language :: Python :: 3
Classifier: Programming Language :: Python :: 3.9
Classifier: Programming Language :: Python :: 3.10
Classifier: Programming Language :: Python :: 3.11
Classifier: Programming Language :: Python :: 3.12
Classifier: Programming Language :: Python :: 3.13
Classifier: Programming Language :: Python :: 3 :: Only
Classifier: Programming Language :: Python :: Implementation :: CPython
Classifier: Programming Language :: Python :: Implementation :: PyPy
Classifier: Topic :: Software Development :: Libraries :: Python Modules
Requires-Python: <4.0.0,>=3.9.0
License-File: LICENSE
License-File: COPYING
Requires-Dist: setuptools>=76.1.0
Requires-Dist: pkg-about>=1.2.10
Provides-Extra: doc
Requires-Dist: Sphinx>=7.4.7; extra == "doc"
Requires-Dist: sphinx-autodoc-typehints>=2.3.0; extra == "doc"
Requires-Dist: sphinx-toolbox>=3.9.0; extra == "doc"
Requires-Dist: sphinx-tabs>=3.4.5; extra == "doc"
Requires-Dist: sphinx-copybutton>=0.5.2; extra == "doc"
Requires-Dist: sphinxcontrib-spelling>=8.0.0; extra == "doc"
Requires-Dist: sphinx-lint>=1.0.0; extra == "doc"
Requires-Dist: restructuredtext-lint>=1.4.0; extra == "doc"
Requires-Dist: nbsphinx>=0.9.7; extra == "doc"
Provides-Extra: test
Requires-Dist: deepdiff>=8.4.2; extra == "test"
Requires-Dist: rich>=13.9.4; extra == "test"
Requires-Dist: ebcdic>=1.1.1; extra == "test"
Requires-Dist: pytest>=8.3.5; extra == "test"
Requires-Dist: cryptography>=44.0.2; (implementation_name != "pypy" or python_version <= "3.10") and extra == "test"
Requires-Dist: multipart>=1.2.1; extra == "test"
Requires-Dist: websockets>=15.0.1; extra == "test"
Requires-Dist: psutil>=7.0.0; extra == "test"
Dynamic: license-file
